[
  {
    "id": 7, 
    "title": "CS101 Course Notes", 
    "img": "notes.jpg", 
    "link": "#", 
    "course": "CS101", 
    "subject": "Computer Science", 
    "description": "Comprehensive lecture notes for Introduction to Programming covering variables, data types, control structures, functions, and basic algorithms with example code snippets.", 
    "author": "Prof. James Wilson", 
    "semester": "Fall 2024",
    "pages": 85,
    "format": "PDF",
    "lastUpdated": "2024-08-15",
    "documentType": "past-paper"
  },
  {
    "id": 8, 
    "title": "Programming Lab Instructions", 
    "img": "lab.jpg", 
    "link": "#", 
    "course": "CS101", 
    "subject": "Computer Science", 
    "description": "Step-by-step instructions for weekly programming labs including environment setup, coding exercises, and submission requirements for each of the 12 lab sessions.", 
    "author": "CS Department", 
    "semester": "Fall 2024",
    "pages": 48,
    "format": "PDF",
    "lastUpdated": "2024-08-20",
    "documentType": "past-paper"
  },
  {
    "id": 14, 
    "title": "CS201 Algorithm Study Guide", 
    "img": "study_guide.jpg", 
    "link": "#", 
    "course": "CS201", 
    "subject": "Computer Science", 
    "description": "Complete study guide covering all algorithm topics including sorting, searching, graph algorithms, dynamic programming, and complexity analysis with practice problems.", 
    "author": "Prof. Emily Taylor", 
    "semester": "Spring 2025",
    "pages": 65,
    "format": "PDF",
    "lastUpdated": "2024-07-30",
    "documentType": "past-paper"
  },
  {
    "id": 15, 
    "title": "MATH150 Formula Sheet", 
    "img": "formula.jpg", 
    "link": "#", 
    "course": "MATH150", 
    "subject": "Mathematics", 
    "description": "Quick reference for all important formulas used in calculus, including derivatives, integrals, series, and multivariable calculus with key examples and applications.", 
    "author": "Math Department", 
    "semester": "Spring 2025",
    "pages": 12,
    "format": "PDF",
    "lastUpdated": "2024-08-05",
    "documentType": "catalogue"
  },
  {
    "id": 16, 
    "title": "Final Exam Preparation Materials", 
    "img": "exam_prep.jpg", 
    "link": "#", 
    "course": "General", 
    "subject": "Study Skills", 
    "description": "Comprehensive review materials for final exams with study strategies, time management tips, sample exam questions, and memory techniques applicable to all courses.", 
    "author": "Student Success Center", 
    "semester": "All",
    "pages": 35,
    "format": "PDF",
    "lastUpdated": "2024-09-01",
    "documentType": "brochure"
  }
]